{"id": "plus_moins", "path": "/home/mfalce/Bureau/pyt_21_novembre_2022/tape_en_cours/plus_moins.py", "mtime": 1669115025, "size": 303, "hash": "82f78f98ddbe4be0b415fa3470bfcd03364200608fd1ea83914a8b838a6b6c4b", "data_mtime": 1669114788, "dependencies": ["builtins", "_typeshed", "abc", "typing", "typing_extensions"], "suppressed": [], "options": {"implicit_reexport": true, "disallow_any_unimported": false, "strict_optional": true, "disallow_incomplete_defs": false, "follow_imports": "silent", "disallow_subclassing_any": false, "warn_no_return": true, "warn_return_any": false, "plugins": [], "allow_untyped_globals": false, "disallow_any_generics": false, "disallow_any_decorated": false, "follow_imports_for_stubs": false, "strict_equality": false, "ignore_errors": false, "check_untyped_defs": false, "allow_redefinition": false, "warn_unused_ignores": false, "always_true": [], "show_none_errors": true, "always_false": [], "local_partial_types": false, "no_implicit_optional": false, "warn_unreachable": false, "bazel": false, "mypyc": false, "disallow_any_expr": false, "disallow_untyped_decorators": false, "strict_optional_whitelist": null, "disallow_any_explicit": false, "platform": "linux", "disallow_untyped_defs": false, "ignore_missing_imports": true, "disallow_untyped_calls": false}, "dep_prios": [5, 30, 30, 30, 30], "dep_lines": [1, 1, 1, 1, 1], "interface_hash": "b38508bde0c208525311e3d30688213e51449ee183ab2d567d5d4b00777e15e1", "version_id": "0.941", "ignore_all": false, "plugin_data": null}